prefsampling/__init__.py
prefsampling/combinatorics.py
prefsampling/inputvalidators.py
prefsampling/approval/__init__.py
prefsampling/approval/euclidean.py
prefsampling/approval/identity.py
prefsampling/approval/impartial.py
prefsampling/approval/noise.py
prefsampling/approval/resampling.py
prefsampling/approval/truncated_ordinal.py
prefsampling/approval/urn.py
prefsampling/approval/utils.py
prefsampling/core/__init__.py
prefsampling/core/composition.py
prefsampling/core/euclidean.py
prefsampling/core/filters.py
prefsampling/core/urn.py
prefsampling/ordinal/__init__.py
prefsampling/ordinal/didi.py
prefsampling/ordinal/euclidean.py
prefsampling/ordinal/groupseparable.py
prefsampling/ordinal/identity.py
prefsampling/ordinal/impartial.py
prefsampling/ordinal/mallows.py
prefsampling/ordinal/plackettluce.py
prefsampling/ordinal/singlecrossing.py
prefsampling/ordinal/singlepeaked.py
prefsampling/ordinal/urn.py
prefsampling/point/__init__.py
prefsampling/point/ball.py
prefsampling/point/cube.py
prefsampling/point/gaussian.py
prefsampling/point/utils.py
prefsampling/tree/__init__.py
prefsampling/tree/balanced.py
prefsampling/tree/caterpillar.py
prefsampling/tree/node.py
prefsampling/tree/schroeder.py
prefsampling-0.1.23.dist-info/LICENSE.md
prefsampling-0.1.23.dist-info/WHEEL
prefsampling-0.1.23.dist-info/METADATA
prefsampling-0.1.23.dist-info/RECORD
