Metadata-Version: 2.3
Name: prefsampling
Version: 0.1.23
Summary: Algorithms to sample preferences of all kinds.
Author-email: Simon Rey <reysimon@orange.fr>, Stanisław Szufa <s.szufa@gmail.com>
Requires-Python: >=3.7
Classifier: Programming Language :: Python :: 3
Classifier: License :: OSI Approved :: GNU General Public License v3 or later (GPLv3+)
Classifier: Operating System :: OS Independent
Classifier: Programming Language :: Python :: 3.7
Classifier: Programming Language :: Python :: 3.8
Classifier: Programming Language :: Python :: 3.9
Classifier: Programming Language :: Python :: 3.10
Classifier: Programming Language :: Python :: 3.11
Classifier: Programming Language :: Python :: 3.12
Requires-Dist: numpy
Requires-Dist: coverage ; extra == "dev"
Requires-Dist: Sphinx ; extra == "dev"
Requires-Dist: sphinx-book-theme ; extra == "dev"
Requires-Dist: sphinxcontrib-napoleon ; extra == "dev"
Requires-Dist: unittest2 ; extra == "dev"
Requires-Dist: matplotlib ; extra == "dev"
Requires-Dist: pandas ; extra == "dev"
Requires-Dist: seaborn ; extra == "dev"
Requires-Dist: scipy ; extra == "dev"
Project-URL: Bug Tracker, https://github.com/COMSOC-Community/prefsampling/issues
Project-URL: Homepage, https://github.com/COMSOC-Community/prefsampling
Provides-Extra: dev
